{
    "name": "Dotfiles Development Container",
    "image": "mcr.microsoft.com/devcontainers/universal:latest",
    "features": {
        "ghcr.io/devcontainers/features/github-cli:1": {},
        "ghcr.io/devcontainers/features/node:1": {
            "version": "lts"
        },
        "ghcr.io/devcontainers/features/python:1": {
            "installTools": true
        }
    },
    "customizations": {
        "vscode": {
            "extensions": [
                "GitHub.copilot",
                "ms-python.python",
                "ms-vscode.js-debug",
                "esbenp.prettier-vscode",
                "dbaeumer.vscode-eslint"
            ],
            "settings": {
                "terminal.integrated.defaultProfile.linux": "zsh",
                "terminal.integrated.profiles.linux": {
                    "zsh": {
                        "path": "/bin/zsh"
                    }
                }
            }
        }
    },
    "postCreateCommand": "git clone https://github.com/stakaya/dotfiles.git ~/dotfiles && ~/dotfiles/setup.sh",
    "remoteUser": "vscode"
}
